{
  "key": "avito-cart",
  "version": "1.0.0",
  "main": {
    "type": "Column",
    "style": {
      "flexDirection": "column",
      "flexGrow": 1
    },
    "children": [
      {
        "type": "Column",
        "style": {
          "flexDirection": "column",
          "flexGrow": 1
        },
        "children": [
          {
            "type": "TopRow"
          },
          {
            "type": "SellerSection",
            "data": {
              "storeName": "Pear Store",
              "rating": "4.8",
              "reviewCount": "643",
              "checked": false
            }
          },
          {
            "type": "CartItem",
            "data": {
              "image": "https://yhfeoztyhuiccuyeghiw.supabase.co/storage/v1/object/public/render-bucket/magsafe.png",
              "price": "4 990 ₽",
              "title": "ЗарядкаMagSafe Charger 15W 1 метр",
              "quantity": 1,
              "checked": true
            }
          },
          {
            "type": "CartItem",
            "data": {
              "image": "https://yhfeoztyhuiccuyeghiw.supabase.co/storage/v1/object/public/render-bucket/airpods.png",
              "price": "15 990 ₽",
              "title": "AirPods Pro 2",
              "quantity": 1,
              "checked": true
            }
          },
          {
            "type": "CartItem",
            "data": {
              "image": "https://yhfeoztyhuiccuyeghiw.supabase.co/storage/v1/object/public/render-bucket/watch2.png",
              "price": "26 591 ₽",
              "title": "Apple Watch 10 42mm Blue",
              "quantity": 1,
              "checked": true
            }
          }
        ]
      },
      {
        "type": "BottomBar"
      }
    ]
  },
  "components": {
    "CartScreen": {
      "type": "Column",
      "style": {
        "flexDirection": "column",
        "flexGrow": 1
      },
      "children": [
        {
          "type": "Column",
          "style": {
            "flexDirection": "column",
            "flexGrow": 1
          },
          "children": [
            {
              "type": "TopRow"
            },
            {
              "type": "SellerSection",
              "data": {
                "storeName": "Pear Store",
                "rating": "4.8",
                "reviewCount": "643",
                "checked": false
              }
            },
            {
              "type": "CartItem",
              "data": {
                "image": "https://yhfeoztyhuiccuyeghiw.supabase.co/storage/v1/object/public/render-bucket/magsafe.png",
                "price": "4 990 ₽",
                "title": "ЗарядкаMagSafe Charger 15W 1 метр",
                "quantity": 1,
                "checked": true
              }
            },
            {
              "type": "CartItem",
              "data": {
                "image": "https://yhfeoztyhuiccuyeghiw.supabase.co/storage/v1/object/public/render-bucket/airpods.png",
                "price": "15 990 ₽",
                "title": "AirPods Pro 2",
                "quantity": 1,
                "checked": true
              }
            },
            {
              "type": "CartItem",
              "data": {
                "image": "https://yhfeoztyhuiccuyeghiw.supabase.co/storage/v1/object/public/render-bucket/watch2.png",
                "price": "26 591 ₽",
                "title": "Apple Watch 10 42mm Blue",
                "quantity": 1,
                "checked": true
              }
            }
          ]
        },
        {
          "type": "BottomBar"
        }
      ]
    },
    "TopRow": {
      "type": "Row",
      "style": {
        "flexDirection": "row",
        "alignItems": "center",
        "paddingHorizontal": 16,
        "paddingVertical": 12
      },
      "children": [
        {
          "type": "Checkbox",
          "style": {
            "borderColor": "#0099F7",
            "borderRadius": 4,
            "marginRight": 16
          },
          "properties": {
            "checked": true,
            "disabled": false
          }
        },
        {
          "type": "Text",
          "style": {
            "fontFamily": "Manrope",
            "fontSize": 15,
            "fontWeight": "500",
            "color": "#000000",
            "marginRight": 16,
            "flexGrow": 1
          },
          "properties": {
            "text": "Выбрать всё"
          }
        },
        {
          "type": "Text",
          "style": {
            "fontFamily": "Manrope",
            "fontSize": 15,
            "fontWeight": "500",
            "color": "#0099F7"
          },
          "properties": {
            "text": "Удалить (3)"
          }
        }
      ]
    },
    "Price": {
      "type": "Text",
      "style": {
        "fontFamily": "Manrope",
        "fontSize": 18,
        "fontWeight": "800",
        "flexShrink": 0,
        "marginBottom": 2
      },
      "properties": {
        "text": {
          "type": "prop",
          "key": "price"
        }
      }
    },
    "ProductTitle": {
      "type": "Text",
      "style": {
        "fontFamily": "Manrope",
        "fontSize": 13,
        "fontWeight": "500",
        "flexMode": "adjustWidth"
      },
      "properties": {
        "text": {
          "type": "prop",
          "key": "title"
        }
      }
    },
    "SellerSection": {
      "type": "Row",
      "style": {
        "flexDirection": "row",
        "alignItems": "center",
        "justifyContent": "flexStart",
        "paddingHorizontal": 16,
        "paddingVertical": 4
      },
      "children": [
        {
          "type": "Checkbox",
          "style": {
            "borderRadius": 4,
            "marginRight": 16
          },
          "properties": {
            "checked": {
              "type": "prop",
              "key": "checked"
            },
            "disabled": false
          }
        },
        {
          "type": "Text",
          "style": {
            "fontFamily": "Manrope",
            "fontSize": 21,
            "fontWeight": "800",
            "marginRight": 8
          },
          "properties": {
            "text": {
              "type": "prop",
              "key": "storeName"
            }
          }
        },
        {
          "type": "Image",
          "style": {
            "width": 16,
            "height": 16,
            "marginRight": 2,
            "alignSelf": "center"
          },
          "properties": {
            "source": "https://yhfeoztyhuiccuyeghiw.supabase.co/storage/v1/object/public/render-bucket/star.png"
          }
        },
        {
          "type": "Text",
          "style": {
            "fontFamily": "Manrope",
            "fontSize": 15,
            "fontWeight": "500",
            "marginRight": 4
          },
          "properties": {
            "text": {
              "type": "prop",
              "key": "rating"
            }
          }
        },
        {
          "type": "Text",
          "style": {
            "fontFamily": "Manrope",
            "fontSize": 15,
            "fontWeight": "500",
            "color": "#A3A3A3"
          },
          "properties": {
            "text": {
              "type": "prop",
              "key": "reviewCount"
            }
          }
        }
      ]
    },
    "BuyWithDelivery": {
      "type": "Text",
      "style": {
        "fontFamily": "Manrope",
        "fontSize": 13,
        "fontWeight": "500",
        "color": "#A168F7"
      },
      "properties": {
        "text": "Купить с доставкой"
      }
    },
    "CountStepper": {
      "type": "Stepper",
      "style": {
        "borderRadius": 12,
        "marginVertical": 10
      },
      "properties": {
        "value": {
          "type": "prop",
          "key": "quantity"
        },
        "minimumValue": 1,
        "maximumValue": 10,
        "disabled": false
      }
    },
    "LikeButton": {
      "type": "Image",
      "style": {
        "borderRadius": 6,
        "width": 28,
        "height": 28
      },
      "properties": {
        "source": "https://yhfeoztyhuiccuyeghiw.supabase.co/storage/v1/object/public/render-bucket/favorites.png"
      }
    },
    "DeleteButton": {
      "type": "Image",
      "style": {
        "borderRadius": 6,
        "width": 28,
        "height": 28
      },
      "properties": {
        "source": "https://yhfeoztyhuiccuyeghiw.supabase.co/storage/v1/object/public/render-bucket/delete.png"
      }
    },
    "ProductImage": {
      "type": "Image",
      "style": {
        "width": 96,
        "height": 96,
        "borderRadius": 12
      },
      "properties": {
        "source": {
          "type": "prop",
          "key": "image"
        }
      }
    },
    "ProductCheckbox": {
      "type": "Checkbox",
      "style": {
        "borderRadius": 4,
        "padding": 4
      },
      "properties": {
        "checked": {
          "type": "prop",
          "key": "checked"
        },
        "disabled": false
      }
    },
    "CartItem": {
      "type": "Row",
      "style": {
        "flexDirection": "row",
        "alignItems": "stretch",
        "gap": 12,
        "paddingHorizontal": 16,
        "paddingVertical": 16
      },
      "children": [
        {
          "type": "ProductCheckbox",
          "data": {
            "checked": {
              "type": "prop",
              "key": "checked"
            }
          }
        },
        {
          "type": "ProductImage",
          "data": {
            "image": {
              "type": "prop",
              "key": "image"
            }
          }
        },
        {
          "type": "Row",
          "style": {
            "flexDirection": "row",
            "flexGrow": 1,
            "flexMode": "adjustWidth",
            "flexShrink": 1
          },
          "children": [
            {
              "type": "Column",
              "style": {
                "flexDirection": "column",
                "gap": 2,
                "flexShrink": 1,
                "flexMode": "adjustWidth"
              },
              "children": [
                {
                  "type": "Price",
                  "data": {
                    "price": {
                      "type": "prop",
                      "key": "price"
                    }
                  }
                },
                {
                  "type": "ProductTitle",
                  "data": {
                    "title": {
                      "type": "prop",
                      "key": "title"
                    }
                  }
                },
                {
                  "type": "CountStepper",
                  "data": {
                    "quantity": {
                      "type": "prop",
                      "key": "quantity"
                    }
                  }
                },
                {
                  "type": "BuyWithDelivery"
                }
              ]
            }
          ]
        },
        {
          "type": "Column",
          "style": {
            "flexDirection": "column",
            "gap": 4,
            "flexShrink": 0
          },
          "children": [
            {
              "type": "LikeButton"
            },
            {
              "type": "DeleteButton"
            }
          ]
        }
      ]
    },
    "BundleSection": {
      "type": "Column",
      "style": {
        "flexDirection": "column",
        "paddingHorizontal": 16,
        "paddingVertical": 20,
        "gap": 16
      },
      "children": [
        {
          "type": "Row",
          "style": {
            "flexDirection": "row",
            "alignItems": "center",
            "gap": 6
          },
          "children": [
            {
              "type": "Text",
              "style": {
                "fontFamily": "Manrope",
                "fontSize": 24,
                "paddingHorizontal": 8,
                "paddingVertical": 4,
                "borderRadius": 8
              },
              "properties": {
                "text": "🎁"
              }
            },
            {
              "type": "Column",
              "style": {
                "flexDirection": "column",
                "flexGrow": 1
              },
              "children": [
                {
                  "type": "Row",
                  "style": {
                    "flexDirection": "row",
                    "justifyContent": "spaceBetween",
                    "alignItems": "center"
                  },
                  "children": [
                    {
                      "type": "Text",
                      "style": {
                        "fontFamily": "Manrope",
                        "fontSize": 14,
                        "fontWeight": "800",
                        "paddingHorizontal": 8,
                        "paddingVertical": 4,
                        "borderRadius": 6
                      },
                      "properties": {
                        "text": "Добавьте ещё 1 товар до скидки 5%"
                      }
                    },
                    {
                      "type": "Button",
                      "style": {
                        "borderRadius": 8,
                        "padding": 8
                      },
                      "properties": {
                        "title": "→"
                      }
                    }
                  ]
                }
              ]
            }
          ]
        },
        {
          "type": "Row",
          "style": {
            "flexDirection": "row",
            "gap": 16
          },
          "children": [
            {
              "type": "BundleItem",
              "data": {
                "image": "watch.png",
                "currentPrice": "26 591 ₽",
                "originalPrice": "27 990 ₽",
                "title": "Apple Watch 10 42mm Blue"
              }
            },
            {
              "type": "BundleItem",
              "data": {
                "image": "shorts.png",
                "currentPrice": "13 314 ₽",
                "originalPrice": "13 320 ₽",
                "title": "Шорты мужские новые 44 размер черные"
              }
            },
            {
              "type": "Column",
              "style": {
                "flexDirection": "column",
                "width": 94,
                "height": 94,
                "borderRadius": 12,
                "justifyContent": "center",
                "alignItems": "center"
              },
              "children": [
                {
                  "type": "Column",
                  "style": {
                    "flexDirection": "column",
                    "alignItems": "center",
                    "gap": 4
                  },
                  "children": [
                    {
                      "type": "Text",
                      "style": {
                        "fontFamily": "Manrope",
                        "fontSize": 15,
                        "fontWeight": "500",
                        "paddingHorizontal": 8,
                        "paddingVertical": 4,
                        "borderRadius": 6
                      },
                      "properties": {
                        "text": "Ещё"
                      }
                    },
                    {
                      "type": "Button",
                      "style": {
                        "borderRadius": 8,
                        "padding": 8
                      },
                      "properties": {
                        "title": "→"
                      }
                    }
                  ]
                }
              ]
            }
          ]
        }
      ]
    },
    "BundleItem": {
      "type": "Column",
      "style": {
        "flexDirection": "column",
        "width": 236,
        "gap": 12
      },
      "children": [
        {
          "type": "Row",
          "style": {
            "flexDirection": "row",
            "alignItems": "center",
            "gap": 12
          },
          "children": [
            {
              "type": "Image",
              "style": {
                "width": 94,
                "height": 94,
                "borderRadius": 12
              },
              "properties": {
                "source": {
                  "type": "prop",
                  "key": "image"
                }
              }
            },
            {
              "type": "Column",
              "style": {
                "flexDirection": "column",
                "gap": 12,
                "width": 130
              },
              "children": [
                {
                  "type": "Column",
                  "style": {
                    "flexDirection": "column",
                    "gap": 4
                  },
                  "children": [
                    {
                      "type": "Row",
                      "style": {
                        "flexDirection": "row",
                        "gap": 6
                      },
                      "children": [
                        {
                          "type": "Text",
                          "style": {
                            "fontFamily": "Manrope",
                            "fontSize": 16,
                            "fontWeight": "800",
                            "paddingHorizontal": 6,
                            "paddingVertical": 2,
                            "borderRadius": 4
                          },
                          "properties": {
                            "text": {
                              "type": "prop",
                              "key": "currentPrice"
                            }
                          }
                        },
                        {
                          "type": "Row",
                          "style": {
                            "flexDirection": "row",
                            "alignItems": "center"
                          },
                          "children": [
                            {
                              "type": "Text",
                              "style": {
                                "fontFamily": "Manrope",
                                "fontSize": 15,
                                "fontWeight": "500",
                                "color": "#757575",
                                "paddingHorizontal": 4,
                                "paddingVertical": 2,
                                "borderRadius": 4
                              },
                              "properties": {
                                "text": {
                                  "type": "prop",
                                  "key": "originalPrice"
                                }
                              }
                            },
                            {
                              "type": "Text",
                              "style": {
                                "fontFamily": "Manrope",
                                "color": "#757575",
                                "paddingHorizontal": 4,
                                "paddingVertical": 2,
                                "borderRadius": 4
                              },
                              "properties": {
                                "text": "─"
                              }
                            }
                          ]
                        }
                      ]
                    },
                    {
                      "type": "Text",
                      "style": {
                        "fontFamily": "Manrope",
                        "fontSize": 11,
                        "fontWeight": "500",
                        "paddingHorizontal": 6,
                        "paddingVertical": 2,
                        "borderRadius": 4
                      },
                      "properties": {
                        "text": {
                          "type": "prop",
                          "key": "title"
                        }
                      }
                    }
                  ]
                },
                {
                  "type": "Button",
                  "style": {
                    "borderRadius": 10,
                    "paddingHorizontal": 12,
                    "paddingVertical": 8,
                    "borderWidth": 1,
                    "borderColor": "#E0E0E0"
                  },
                  "properties": {
                    "title": "В корзину"
                  }
                }
              ]
            }
          ]
        }
      ]
    },
    "BottomBar": {
      "type": "Column",
      "style": {
        "flexDirection": "column",
        "paddingHorizontal": 16,
        "paddingVertical": 16,
        "borderRadius": 28,
        "shadowColor": "#000000",
        "shadowOffset": {
          "width": 0,
          "height": 4
        },
        "shadowOpacity": 0.8,
        "shadowRadius": 24
      },
      "children": [
        {
          "type": "Row",
          "style": {
            "flexDirection": "row",
            "justifyContent": "spaceBetween",
            "alignItems": "center",
            "marginBottom": 16
          },
          "children": [
            {
              "type": "Column",
              "style": {
                "flexDirection": "column"
              },
              "children": [
                {
                  "type": "Text",
                  "style": {
                    "fontFamily": "Manrope",
                    "fontSize": 11,
                    "fontWeight": "500",
                    "color": "#000000",
                    "paddingHorizontal": 8,
                    "paddingVertical": 4,
                    "borderRadius": 6
                  },
                  "properties": {
                    "text": "3 товара"
                  }
                },
                {
                  "type": "Text",
                  "style": {
                    "fontFamily": "Manrope",
                    "fontSize": 21,
                    "fontWeight": "800",
                    "paddingHorizontal": 12,
                    "paddingVertical": 6,
                    "borderRadius": 8
                  },
                  "properties": {
                    "text": "120 979 ₽"
                  }
                }
              ]
            },
            {
              "type": "Button",
              "style": {
                "borderRadius": 16,
                "paddingHorizontal": 18,
                "paddingVertical": 17,
                "backgroundColor": "#965EEB"
              },
              "properties": {
                "titleStyle": {
                  "color": "#FFFFFF",
                  "fontWeight": "500",
                  "fontSize": 15
                },
                "title": "Оформить доставку"
              }
            }
          ]
        }
      ]
    }
  }
}